cusip_generator/__init__.py
cusip_generator/main.py
cusip_generator/utils.py
tests/__init__.py
tests/test_calculate_check_digit.py
tests/test_compose_eight_digits_cusip.py
tests/test_guess_year.py
tests/test_main.py
tests/test_validate.py
cusip_generator-0.0.3.dist-info/LICENSE
cusip_generator-0.0.3.dist-info/METADATA
cusip_generator-0.0.3.dist-info/WHEEL
cusip_generator-0.0.3.dist-info/top_level.txt
cusip_generator-0.0.3.dist-info/RECORD
